setup.cfg
setup.py
rss_calling/__init__.py
rss_calling/cli.py
rsscalling.egg-info/PKG-INFO
rsscalling.egg-info/SOURCES.txt
rsscalling.egg-info/dependency_links.txt
rsscalling.egg-info/entry_points.txt
rsscalling.egg-info/not-zip-safe
rsscalling.egg-info/requires.txt
rsscalling.egg-info/top_level.txt