Metadata-Version: 1.1
Name: rsscalling
Version: 0.0.3
Summary: Rss Calling is a CLI tool for reading news from RSS feeds
Home-page: UNKNOWN
Author: Davide Salamino
Author-email: UNKNOWN
License: GPL
Platform: any
Classifier: Development Status :: 4 - Beta
Classifier: Environment :: Console
Classifier: Intended Audience :: End Users/Desktop
Classifier: License :: OSI Approved :: GNU General Public License (GPL)
Classifier: Operating System :: OS Independent
Classifier: Programming Language :: Python
Classifier: Programming Language :: Python :: 2
Classifier: Programming Language :: Python :: 3
